__init__.py
talkyleo/__init__.py
talkyleo/polly.py
talkyleo/tts.py
talkyleo-0.1.11.dist-info/LICENSE
talkyleo-0.1.11.dist-info/METADATA
talkyleo-0.1.11.dist-info/WHEEL
talkyleo-0.1.11.dist-info/top_level.txt
talkyleo-0.1.11.dist-info/RECORD
